django_tutelary-0.1.22.dist-info/DESCRIPTION.rst
django_tutelary-0.1.22.dist-info/METADATA
django_tutelary-0.1.22.dist-info/RECORD
django_tutelary-0.1.22.dist-info/WHEEL
django_tutelary-0.1.22.dist-info/metadata.json
django_tutelary-0.1.22.dist-info/top_level.txt
tutelary/__init__.py
tutelary/apps.py
tutelary/backends.py
tutelary/decorators.py
tutelary/engine.py
tutelary/exceptions.py
tutelary/mixins.py
tutelary/models.py
tutelary/wildtree.py
tutelary/__pycache__/__init__.cpython-35.pyc
tutelary/__pycache__/apps.cpython-35.pyc
tutelary/__pycache__/backends.cpython-35.pyc
tutelary/__pycache__/decorators.cpython-35.pyc
tutelary/__pycache__/engine.cpython-35.pyc
tutelary/__pycache__/exceptions.cpython-35.pyc
tutelary/__pycache__/mixins.cpython-35.pyc
tutelary/__pycache__/models.cpython-35.pyc
tutelary/__pycache__/wildtree.cpython-35.pyc
tutelary/migrations/0001_initial.py
tutelary/migrations/__init__.py
tutelary/migrations/__pycache__/0001_initial.cpython-35.pyc
tutelary/migrations/__pycache__/__init__.cpython-35.pyc
