Metadata-Version: 2.0
Name: django-tutelary
Version: 0.1.22
Summary: Policy-based permissions for Django.
Home-page: https://github.com/Cadasta/django-tutelary
Author: Ian Ross
Author-email: iross@cadasta.org
License: GNU AGPL v3
Platform: UNKNOWN
Classifier: Development Status :: 3 - Alpha
Classifier: Environment :: Web Environment
Classifier: Framework :: Django :: 1.9
Classifier: Intended Audience :: Developers
Classifier: License :: OSI Approved :: GNU Affero General Public License v3
Classifier: Operating System :: OS Independent
Classifier: Natural Language :: English
Classifier: Programming Language :: Python :: 3.5
Classifier: Topic :: Internet :: WWW/HTTP
Requires-Dist: Django (>=1.9)
Requires-Dist: django-audit-log (>=0.7.0)
